PC_Adder.sv
`timescale 1ns/1ps
module PC_Adder(
  input[7:0] In,
  output[7:0] Out
);
  
  assign Out = In+1;
endmodule

MUX.sv
`timescale 1ns/1ps
module MUX(
  input[7:0] In1, In2,
  input sel,
  output[7:0] Out
);
  
  assign Out = (sel==1)?In2:In1;
endmodule

Data_Memory.sv
`timescale 1ns/1ps
module Data_Memory(
  input E, WE, clk,
  input[3:0] Addr,
  input[7:0] DI,
  output[7:0] DO
);
  
  reg[7:0] DMem[15:0];
  
  assign DO = (E==1)?DMem[Addr]:0;
  
  always @(posedge clk)
    begin
      if (E && WE)
        begin
          DMem[Addr] <= DI;
      	end
    end
endmodule

Program_Memory.sv
`timescale 1ns/1ps
module Program_Memory(
  input E, LE, clk,
  input[7:0] Addr, LA,
  input [11:0] LI,
  output[11:0] I
);

  reg[11:0] PMem[255:0];
  assign I = (E)?PMem[Addr]:12'b0;
  
  always @(posedge clk)
    begin
      if (LE==1)
        begin
          PMem[LA] = LI;
        end
    end
  
endmodule

ALU.sv
`timescale 1ns/1ps
module ALU(
  input[3:0] mode, CFlags,
  input[7:0] Operand1, Operand2,
  input E,
  output [7:0] Out,
  output [3:0] Flags
);
  
  reg[8:0] Res;
  reg Z,C,S,O;
  assign Out = Res[7:0];
  
  always @(*)
    begin
      Z = !(|Res[7:0]);
  	  O = Res[8];
    end
  
  assign Flags = {Z,C,S,O};
  
  
  always @(*)
    begin
      Res = 9'b000000000;
      case(mode)
        4'h0:
          begin
            Res = Operand1 + Operand2;
            C = Res[8];
          end
        4'h1:
          begin
            Res = Operand1 - Operand2;
            S = (Operand1 < Operand2)?1'b1:1'b0;
          end
        4'h2:
          Res = Operand1;
        4'h3:
          Res = Operand2;
        4'h4:
          Res = Operand1 & Operand2;
        4'h5:
          Res = Operand1 | Operand2;
        4'h6:
          Res = Operand1 ^ Operand2;
        4'h7:
          begin
            Res = Operand2 - Operand1;
            S = (Operand2 < Operand1)?1'b1:1'b0;
          end
        4'h8:
          Res = Operand2 + 1;
        4'h9:
          Res = Operand2 - 1;
        4'ha:
          Res = (Operand2 << Operand1[2:0]) | (Operand2 >> 8-Operand1[2:0]);
        4'hb:
          Res = (Operand2 >> Operand1[2:0]) | (Operand2 << 8-Operand1[2:0]);
        4'hc:
          Res = Operand2 << Operand1[2:0];
        4'hd:
          Res = Operand2 >> Operand1[2:0];
        4'he:
          Res = Operand2 >>> Operand1[2:0];
        4'hf:
          begin
            Res = 0 - Operand2;
            S = (0 < Operand2)?1'b1:1'b0;
          end
        default:
          Res = Operand1+Operand2;            
      endcase
    end
endmodule

Control_Unit.sv
`timescale 1ns/1ps
module Control_Unit(
  input[1:0] present_state,
  input [11:0] IR,
  input [3:0] SR,
  output reg PC_E, Acc_E, SR_E, IR_E, DR_E, PMem_E, DMem_E, DMem_WE, ALU_E, MUX1_sel, MUX2_sel, PMem_LE,
  output reg[3:0] ALU_mode
);
  
  parameter LOAD = 2'b00, 
  			FETCH = 2'b01,
  			DECODE = 2'b10,
  			EXECUTE = 2'b11;
  
  always @(*)
    begin
      PC_E = 0;
      Acc_E = 0;
      SR_E = 0;
      IR_E = 0;
      DR_E = 0;
      PMem_E = 0;
      DMem_E = 0;
      DMem_WE = 0;
      ALU_E = 0;
      MUX1_sel = 1'b0;
      MUX2_sel = 1'b0;
      ALU_mode = 4'b0000;
      PMem_LE = 0;
      
      if(present_state == LOAD)
        begin
          PMem_LE = 1;
          PMem_E = 1;
        end
      
      else if(present_state == FETCH)
        begin
          IR_E = 1;
          PMem_E = 1;
        end
      
      else if(present_state == DECODE)
        begin
          if (IR[11:9] == 4'b001)
            begin
              DR_E = 1;
              DMem_E = 1;
            end
        end
      
      else if(present_state == EXECUTE)
        begin
          if (IR[11:8] == 4'b0000)
            begin
              PC_E = 1;
              MUX1_sel = 1;
            end
          
          else if(IR[11:8] == 4'b0001)
            begin
              PC_E = 1;
              MUX1_sel = 0;
            end
          
          else if(IR[11:9] == 3'b001)
            begin
              PC_E = 1;
              Acc_E = IR[8];
              SR_E = 1;
              DMem_E = !(IR[8]);
              DMem_WE = !(IR[8]);
              ALU_E = 1;
              ALU_mode = IR[7:4];
              MUX1_sel = 1;
              MUX2_sel = 1;
            end
          
          else if(IR[11:10] == 2'b01)
            begin
              PC_E = 1;
              MUX1_sel = SR[IR[9:8]];
            end
          
          else if(IR[11] == 1'b1)
            begin
              PC_E = 1;
              Acc_E = 1;
              SR_E = 1;
              ALU_E = 1;
              ALU_mode = {1'b0,IR[10:8]};
              MUX1_sel = 1;
              MUX2_sel = 0;
            end  
          else
            begin
              PC_E = 1;
              MUX1_sel = 0;
            end
        end
    end
endmodule

design.sv
`include "ALU.sv"
`include "Program_Memory.sv"
`include "Data_Memory.sv"
`include "PC_Adder.sv"
`include "MUX.sv"
`include "Control_Unit.sv"
`timescale 1ns/1ps
module Microcontroller(
  input clk, rst
); 
  
  parameter InsNumber = 4'd10;
  
  reg[11:0] Instruction_Mem[9:0];
  reg load_done;
  
  reg[7:0] PC, Acc, load_addr;
  reg[3:0] SR;
  reg[11:0] IR, PMem_LI;
  reg[7:0] DR, PMem_LA;
  wire PMem_LE;
  wire IR_E, DR_E, Acc_E, SR_E;
  wire[11:0] load_instr;
  
  wire[11:0] IR_Wire;

  wire ALU_E, PMem_E, DMem_E, DMem_WE, MUX1_sel, MUX2_sel, PC_E;
  wire[3:0] ALU_mode, SR_updated;
  wire[7:0] MUX2_Out, ALU_Out, DMem_DO, Adder_Out, PC_Wire;
  
  parameter LOAD = 2'b00, 
  			FETCH = 2'b01,
  			DECODE = 2'b10,
  			EXECUTE = 2'b11;
  reg[1:0] present_state, next_state;
  
  initial
    begin
      $readmemb("Instructions.txt", Instruction_Mem, 0,9);
      $dumpfile("dump.vcd");
      $dumpvars(1, Microcontroller);
    end
  
  Control_Unit CU(.present_state(present_state),
                  .IR(IR),
                  .SR(SR),
                  .PC_E(PC_E),
                  .Acc_E(Acc_E),
                  .SR_E(SR_E),
                  .IR_E(IR_E),
                  .DR_E(DR_E),
                  .PMem_E(PMem_E),
                  .DMem_E(DMem_E),
                  .DMem_WE(DMem_WE),
                  .ALU_E(ALU_E),
                  .MUX1_sel(MUX1_sel),
                  .MUX2_sel(MUX2_sel),
                  .PMem_LE(PMem_LE),
                  .ALU_mode(ALU_mode)
                 );                 
  
  ALU alu(.E(ALU_E),
          .Operand1(Acc),
          .Operand2(MUX2_Out),
          .mode(ALU_mode),
          .CFlags(SR),
          .Out(ALU_Out),
          .Flags(SR_updated)
         );
  
  Program_Memory PMem(.clk(clk),
                      .E(PMem_E),
                      .Addr(PC),
                      .I(IR_Wire),
                      .LE(PMem_LE),
                      .LA(load_addr),
                      .LI(load_instr)
                     );
  
  Data_Memory DMem(.clk(clk),
                   .E(DMem_E),
                   .WE(DMem_WE),
                   .Addr(IR[3:0]),
                   .DI(ALU_Out),
                   .DO(DMem_DO)
                  );
  
  MUX mux1(.In1(IR[7:0]),
           .In2(Adder_Out),
           .sel(MUX1_sel),
           .Out(PC_Wire)
          );
  
  MUX mux2(.In1(IR[7:0]),
           .In2(DR),
           .sel(MUX2_sel),
           .Out(MUX2_Out)
          );
  
  PC_Adder Adder(.In(PC),
                 .Out(Adder_Out)
                );
  
  always @(posedge clk)
    begin
      if (rst)
        begin
          load_addr <= 0;
          load_done <= 0;
        end
      else if(PMem_LE)
        begin
          if(~load_done)
          	load_addr <= load_addr + 8'h01;
          if (load_addr == InsNumber)
            begin
              load_addr <= 8'd0;
              load_done <= 8'b1;
            end
          else
            load_done <= 1'b0;
        end
    end
  
  assign load_instr = Instruction_Mem[load_addr];
        
  
  always @(posedge clk)
    begin
      if (rst)
        begin
          present_state <= LOAD;
          PC <= 0;
          Acc <= 0;
          SR <= 0;
          PMem_LI <= 0;
          PMem_LA <= 0;
        end
      
      else
        begin
          if(PC_E)
            PC <= PC_Wire;
          if(Acc_E)
            Acc <= ALU_Out;
          if (SR_E)
            SR <= SR_updated;
        end
    end
  
  always @(posedge clk)
    begin
      if(DR_E)
        DR <= DMem_DO;
      if(IR_E)
        IR <= IR_Wire;
    end
  
  always @(posedge clk) present_state <= next_state;

  always @(*)
    begin
      case(present_state)
        LOAD:
          begin
          	PC = 0;
            IR = 0;
            DR = 0;
            Acc = 0;
            SR = 0;
            if(load_done)
            	next_state = FETCH;
            else
              next_state = LOAD;
          end
        
        FETCH:
          begin
            next_state = DECODE;
          end
        
        DECODE:
          begin
            next_state = EXECUTE;
          end
          
        EXECUTE:
          begin
            next_state = FETCH;
          end
      endcase
    end
endmodule

testbench.sv
`timescale 1ns/1ps
module tb;
  reg clk, rst;
  
  Microcontroller uc(
    clk, rst
  );
  
  always #10 clk = ~clk;

  initial
    begin
      
      clk = 0;
      rst = 1;
      #100
      rst = 0;
      
      #1000
      $finish;
    end
endmodule

dump.vcd
$date
	Sun Jan  3 12:05:11 2021
$end
$version
	Icarus Verilog
$end
$timescale
	1ps
$end
$scope module tb $end
$scope module uc $end
$var wire 1 ! ALU_E $end
$var wire 8 " ALU_Out [7:0] $end
$var wire 4 # ALU_mode [3:0] $end
$var wire 1 $ Acc_E $end
$var wire 8 % Adder_Out [7:0] $end
$var wire 8 & DMem_DO [7:0] $end
$var wire 1 ' DMem_E $end
$var wire 1 ( DMem_WE $end
$var wire 1 ) DR_E $end
$var wire 1 * IR_E $end
$var wire 12 + IR_Wire [11:0] $end
$var wire 1 , MUX1_sel $end
$var wire 8 - MUX2_Out [7:0] $end
$var wire 1 . MUX2_sel $end
$var wire 1 / PC_E $end
$var wire 8 0 PC_Wire [7:0] $end
$var wire 1 1 PMem_E $end
$var wire 1 2 PMem_LE $end
$var wire 1 3 SR_E $end
$var wire 4 4 SR_updated [3:0] $end
$var wire 1 5 clk $end
$var wire 12 6 load_instr [11:0] $end
$var wire 1 7 rst $end
$var reg 8 8 Acc [7:0] $end
$var reg 8 9 DR [7:0] $end
$var reg 12 : IR [11:0] $end
$var reg 8 ; PC [7:0] $end
$var reg 8 < PMem_LA [7:0] $end
$var reg 12 = PMem_LI [11:0] $end
$var reg 4 > SR [3:0] $end
$var reg 8 ? load_addr [7:0] $end
$var reg 1 @ load_done $end
$var reg 2 A next_state [1:0] $end
$var reg 2 B present_state [1:0] $end
$upscope $end
$upscope $end
$enddefinitions $end
#0
$dumpvars
bx B
bx A
x@
bx ?
bx >
bx =
bx <
bx ;
bx :
bx 9
bx 8
17
bx 6
05
bx 4
x3
x2
x1
bx 0
x/
x.
bx -
x,
bx +
x*
x)
x(
x'
bx &
bx %
x$
bx #
bx "
x!
$end
#10000
b0 "
b10x0 4
b0 0
b0 &
b0 -
b1 %
12
b0 #
0.
0,
0!
0(
0'
11
0)
0*
03
0$
0/
b0 A
b0 9
b0 :
0@
b0 ?
b0 6
b0 <
b0 =
b0 >
b0 8
b0 ;
b0 B
15
#20000
05
#30000
b0 +
15
#40000
05
#50000
15
#60000
05
#70000
15
#80000
05
#90000
15
#100000
05
07
#110000
b1 ?
b101100000001 6
15
#120000
05
#130000
b10 ?
b1000100000 6
15
#140000
05
#150000
b11 ?
b1100000000 6
15
#160000
05
#170000
b100 ?
b1000000000 6
15
#180000
05
#190000
b101 ?
b1100010000 6
15
#200000
05
#210000
b110 ?
b1000010000 6
15
#220000
05
#230000
b111 ?
b1101110000 6
15
#240000
05
#250000
b1000 ?
b1001110000 6
15
#260000
05
#270000
b1001 ?
b100001001 6
15
#280000
05
#290000
b1010 ?
bx 6
15
#300000
05
#310000
b1 A
1@
b0 6
b0 ?
15
#320000
05
#330000
1*
02
11
b10 A
0@
b1 B
15
#340000
05
#350000
01
0*
b11 A
b10 B
15
#360000
05
#370000
b1 0
1,
1/
b1 A
b11 B
15
#380000
05
#390000
b101100000001 +
b0 0
11
1*
0,
0/
b10 A
b10 %
b1 B
b1 ;
15
#400000
05
#410000
b0x0 4
b1 "
b1 0
b1 -
b0 +
01
0*
b11 A
b101100000001 :
b10 B
15
#420000
05
#430000
b10 0
1,
b11 #
1!
13
1$
1/
b1 A
b11 B
15
#440000
05
#450000
b10 "
b1000100000 +
b1 0
b11 %
11
1*
b0 #
0,
0!
03
0$
0/
b10 A
b0x0 >
b1 8
b10 ;
b1 B
15
#460000
05
#470000
b100001 "
b100000 0
b100000 -
bx &
b0 +
b11 A
1'
1)
01
0*
b10 B
b1000100000 :
15
#480000
05
#490000
b1 "
bx -
b11 0
1.
1,
b10 #
1!
1(
13
1/
1'
0)
b1 A
bx 9
b11 B
15
#500000
05
#510000
b100001 "
b1100000000 +
b100000 -
b100000 0
11
1*
b0 #
0.
0,
0!
0(
0'
03
0/
b10 A
b100 %
b0 &
b1 B
b11 ;
15
#520000
05
#530000
b1 "
b0 0
b0 -
b1 &
b0 +
1'
1)
01
0*
b11 A
b1100000000 :
b10 B
15
#540000
05
#550000
b10 "
b1 -
b100 0
b0 &
1.
1,
1!
13
1$
1/
0'
0)
b1 A
b11 B
b1 9
15
#560000
05
#570000
b10 "
b1000000000 +
b0 -
b0 0
b101 %
11
1*
0.
0,
0!
03
0$
0/
b10 A
b10 8
b100 ;
b1 B
15
#580000
05
#590000
b1 &
b0 +
b11 A
1'
1)
01
0*
b10 B
b1000000000 :
15
#600000
05
#610000
b11 "
b1 -
b101 0
1.
1,
1!
1(
13
1/
1'
0)
b1 A
b11 B
15
#620000
05
#630000
b10 "
b1100010000 +
b0 -
b0 0
11
1*
0.
0,
0!
0(
0'
03
0/
b10 A
b110 %
b0 &
b1 B
b101 ;
15
#640000
05
#650000
b10010 "
b10000 0
b10000 -
b11 &
b0 +
1'
1)
01
0*
b11 A
b1100010000 :
b10 B
15
#660000
05
#670000
b11111111 "
b11 -
b110 0
b11 4
b0 &
1.
1,
b1 #
1!
13
1$
1/
0'
0)
b1 A
b11 B
b11 9
15
#680000
05
#690000
b1111 "
b1000010000 +
b10000 -
b10000 0
b111 4
b111 %
11
1*
b0 #
0.
0,
0!
03
0$
0/
b10 A
b11 >
b11111111 8
b110 ;
b1 B
15
#700000
05
#710000
b11 &
b0 +
b11 A
1'
1)
01
0*
b10 B
b1000010000 :
15
#720000
05
#730000
b11111100 "
b11 -
b111 0
b100 4
1.
1,
b1 #
1!
1(
13
1/
1'
0)
b1 A
b11 B
15
#740000
05
#750000
b101 4
b1111 "
b1101110000 +
b10000 -
b10000 0
b10 A
11
1*
b0 #
0.
0,
0!
0(
0'
03
0/
b1000 %
b0 &
b1 B
b100 >
b111 ;
15
#760000
05
#770000
b1101111 "
b1110000 0
b1110000 -
b11111100 &
b0 +
1'
1)
01
0*
b11 A
b1101110000 :
b10 B
15
#780000
05
#790000
b11111101 "
b11111100 -
b1000 0
b111 4
b0 &
1.
1,
b111 #
1!
13
1$
1/
0'
0)
b1 A
b11 B
b11111100 9
15
#800000
05
#810000
b1101101 "
b1001110000 +
b1110000 -
b1110000 0
b1001 %
11
1*
b0 #
0.
0,
0!
03
0$
0/
b10 A
b111 >
b11111101 8
b1000 ;
b1 B
15
#820000
05
#830000
b11111100 &
b0 +
b11 A
1'
1)
01
0*
b10 B
b1001110000 :
15
#840000
05
#850000
b11111111 "
b11111100 -
b1001 0
1.
1,
b111 #
1!
1(
13
1/
1'
0)
b1 A
b11 B
15
#860000
05
#870000
b1101101 "
b100001001 +
b1110000 -
b1110000 0
11
1*
b0 #
0.
0,
0!
0(
0'
03
0/
b10 A
b1010 %
b0 &
b1 B
b1001 ;
15
#880000
05
#890000
b110 "
b1001 0
b1001 -
b0 +
01
0*
b11 A
b100001001 :
b10 B
15
#900000
05
#910000
1/
b1 A
b11 B
15
#920000
05
#930000
b100001001 +
11
1*
0/
b10 A
b1 B
15
#940000
05
#950000
b0 +
01
0*
b11 A
b10 B
15
#960000
05
#970000
1/
b1 A
b11 B
15
#980000
05
#990000
b100001001 +
11
1*
0/
b10 A
b1 B
15
#1000000
05
#1010000
b0 +
01
0*
b11 A
b10 B
15
#1020000
05
#1030000
1/
b1 A
b11 B
15
#1040000
05
#1050000
b100001001 +
11
1*
0/
b10 A
b1 B
15
#1060000
05
#1070000
b0 +
01
0*
b11 A
b10 B
15
#1080000
05
#1090000
1/
b1 A
b11 B
15
